Metadata-Version: 2.1
Name: GeoDataProcessor
Version: 1.0
Summary: Fast satellite image data processing library
Home-page: https://github.com/homomorfism/GeoDataProcessor/
Author: Shamil Arslanov
Author-email: arsl.sh056@mail.ru
License: MIT
Keywords: tiff shp images geo
Platform: UNKNOWN
Classifier: Development Status :: 3 - Alpha
License-File: LICENSE
